{
  "Episode": {
    "Title": "Ansatsu Kyoushitsu (TV)",
    "NumberEpisode": "4",
    "TitleOfEpisode": "",
    "Type": "Napisy PL",
    "AudioLanguage": "Japo\u0144ski",
    "SubtitleLanguage": "Polski",
    "LinkToEpisode": "https://www.cda.pl/video/551975638",
    "TranslationCreator": "anime-odcinki.pl",
    "TranslationCreatorAdditionalInformation": ""
  },
  "Link360p": "\u0022https://.cda.pl/a6kOkf_djmvmjQzr6zjAUQ/1690172775/.mp4\u0022",
  "Link480p": "\u0022https://vwaw063.cda.pl/RjlP7Z7UY47S6U7mp7D0RQ/1690172774/lq0d3b37b9c49ced741b8e42960fd44a52.mp4\u0022",
  "Link720p": "\u0022https://.cda.pl/p_5d-zYDBpqhyTWXFu_YLA/1690172772/.mp4\u0022",
  "Link1080p": "\u0022https://.cda.pl/LiJR99XyTRJtkh4Ir0sBdw/1690172771/.mp4\u0022"
}