{
  "LinkToIFrame": "https://www.dailymotion.com/embed/video/k39IiXrAXx7RENA2LI6?hideInfos=1\u0026forcedQuality=hd720\u0026logo=1%7C%7C",
  "TitleAnime": "Youkoso Jitsuryoku Shijou Shugi no Kyoushitsu e 3rd Season",
  "TitleEpisode": "Ci, kt\u00F3rzy nie pami\u0119taj\u0105 przesz\u0142o\u015Bci, s\u0105 skazani na jej powtarzanie",
  "Number": "8",
  "Translator": "https://cdn.ogladajanime.pl/images/sub/0.png",
  "A": "https://cdn.ogladajanime.pl/images/flags/jp.png",
  "S": "https://cdn.ogladajanime.pl/images/flags/pl.png"
}